tethys_cdsapi/__init__.py
tethys_cdsapi/downloader.py
tethys_cdsapi/utils.py
tethys_cdsapi/tests/__init__.py
tethys_cdsapi/tests/parameters.yml
tethys_cdsapi/tests/testing.py
tethys_cdsapi/tests/utest_downloader.py
tethys_cdsapi-0.3.0.dist-info/METADATA
tethys_cdsapi-0.3.0.dist-info/WHEEL
tethys_cdsapi-0.3.0.dist-info/licenses/LICENSE
tethys_cdsapi-0.3.0.dist-info/RECORD
