Metadata-Version: 2.4
Name: tethys-cdsapi
Version: 0.3.0
Summary: utilities for downloading and processing CDS data
Project-URL: Homepage, https://github.com/tethys-ts/tethys-cdsapi
Author-email: Mike Kittridge <mullenkamp1@gmail.com>
License-Expression: Apache-2.0
License-File: LICENSE
Keywords: cdsapi,tethys
Classifier: Development Status :: 3 - Alpha
Classifier: Intended Audience :: Developers
Classifier: License :: OSI Approved :: Apache Software License
Classifier: Programming Language :: Python :: 3
Classifier: Topic :: Software Development :: Build Tools
Requires-Dist: cdsapi>=0.7.2
Requires-Dist: pandas<3
Requires-Dist: requests
Requires-Dist: urllib3
